[
    {
        "Title": "Lembre-se do que Deus j\u00e1 fez",
        "ID": "ae7d336b87949cb28d1efa60ae484570",
        "Description": "Bendiga o Senhor a minha alma!\nN\u00e3o esque\u00e7a nenhuma de suas b\u00ean\u00e7\u00e3os!\n- Salmos 103:2\n\nHoje a Palavra de Deus nos convida a olhar para tr\u00e1s e recordar tudo o que Ele j\u00e1 fez por n\u00f3s. A mem\u00f3ria \u00e9 uma arma poderosa contra o des\u00e2nimo, pois nos lembra que Aquele que nos sustentou ontem continua presente hoje e permanecer\u00e1 fiel amanh\u00e3.\nQuando Israel enfrentava desertos, Deus sempre instru\u00eda o povo a lembrar. Lembrar do mar que se abriu, do man\u00e1 que desceu do c\u00e9u, da \u00e1gua que brotou da rocha. Esses testemunhos n\u00e3o eram apenas hist\u00f3rias, mas marcos da fidelidade d'Ele. Assim tamb\u00e9m \u00e9 conosco: cada livramento, cada provis\u00e3o, cada ora\u00e7\u00e3o respondida \u00e9 um memorial da bondade do Senhor.\nMuitas vezes, diante de um novo desafio, esquecemos quantas vezes Deus j\u00e1 nos levantou. Mas Ele continua sendo o mesmo Deus que cura, restaura, fortalece e transforma. A mem\u00f3ria dos Seus feitos reacende a f\u00e9, renova a esperan\u00e7a e nos devolve a coragem para avan\u00e7ar.\nLembre-se das portas que Ele abriu, dos caminhos que preparou quando tudo parecia fechado. Lembre-se da paz que Ele derramou em momentos de tempestade, da for\u00e7a que veio quando as suas pr\u00f3prias for\u00e7as se esgotaram. Lembre-se das promessas que Ele sussurrou ao seu cora\u00e7\u00e3o nos dias escuros.\nAo recordar, nosso cora\u00e7\u00e3o se enche de gratid\u00e3o. E a gratid\u00e3o abre espa\u00e7o para nova f\u00e9, novo \u00e2nimo e novas expectativas no Senhor. Deus n\u00e3o muda. Sua fidelidade permanece de gera\u00e7\u00e3o em gera\u00e7\u00e3o.\nPor isso, n\u00e3o permita que o peso do presente apague as vit\u00f3rias do passado. O Deus que j\u00e1 fez grandes coisas continuar\u00e1 fazendo. Confie, espere e permane\u00e7a firme, porque Ele \u00e9 fiel.\nRecordando e fortalecendo a f\u00e9\n\nEscreva em um caderno os livramentos, respostas de ora\u00e7\u00e3o e provis\u00f5es que j\u00e1 recebeu, revisando sempre que enfrentar momentos de inseguran\u00e7a ou dificuldade.\nCompartilhe testemunhos pessoais com amigos ou familiares, fortalecendo sua f\u00e9 e tamb\u00e9m edificando aqueles que precisam ser lembrados da fidelidade de Deus.\nSepare alguns minutos di\u00e1rios para agradecer especificamente por feitos passados de Deus, treinando sua mente a reconhecer continuamente Sua bondade constante.\n\nPara orar:\n\nSenhor Deus, agrade\u00e7o por tua fidelidade que me sustenta todos os dias. Obrigado pelas vit\u00f3rias, provis\u00f5es e cuidados que j\u00e1 recebi. Renova minha mem\u00f3ria para que eu jamais esque\u00e7a teus feitos. Que minha vida reflita constante gratid\u00e3o e confian\u00e7a em tua presen\u00e7a amorosa. Am\u00e9m.\n\nVeja tamb\u00e9m: Exemplos de gratid\u00e3o na B\u00edblia: 8 hist\u00f3rias para inspirar",
        "Link": "https://www.bibliaon.com/a_gratidao_de_paulo/"
    },
    {
        "Title": "Superando as tribula\u00e7\u00f5es atrav\u00e9s da f\u00e9",
        "ID": "7d7b831a3718f6a6f59930809631cdbf",
        "Description": "\"Eu disse essas coisas para que em mim voc\u00eas tenham paz. Neste mundo voc\u00eas ter\u00e3o afli\u00e7\u00f5es; contudo, tenham \u00e2nimo! Eu venci o mundo\".\n- Jo\u00e3o 16:33\n\nAs atribula\u00e7\u00f5es fazem parte da nossa jornada de f\u00e9. Ningu\u00e9m est\u00e1 imune \u00e0s lutas, perdas, d\u00favidas ou momentos de profunda ang\u00fastia. Contudo, a Palavra nos lembra que n\u00e3o caminhamos sozinhos. Em cada batalha, Deus permanece ao nosso lado com Sua for\u00e7a e nos ensinando a enxergar al\u00e9m da dor.\nVencer as atribula\u00e7\u00f5es com f\u00e9 n\u00e3o \u00e9 negar a dificuldade, mas enfrent\u00e1-la com a certeza de que o Senhor est\u00e1 no controle.\nA f\u00e9 \u00e9 o escudo que nos protege dos ataques da desesperan\u00e7a. Quando as circunst\u00e2ncias parecem maiores que n\u00f3s, \u00e9 justamente a\u00ed que precisamos recordar quem Deus \u00e9: o nosso ref\u00fagio seguro, socorro bem presente na tribula\u00e7\u00e3o. Ele transforma l\u00e1grimas em for\u00e7a, d\u00favidas em aprendizado e quedas em novos passos de vit\u00f3ria. Crer, mesmo quando nada faz sentido, \u00e9 declarar que a \u00faltima palavra pertence ao Pai.\nPara vencer os dias dif\u00edceis, \u00e9 essencial cultivar uma vida de ora\u00e7\u00e3o. \u00c9 na presen\u00e7a de Deus que a alma encontra descanso e renovo. A ora\u00e7\u00e3o realinha nossos pensamentos com os pensamentos do Senhor e fortalece o cora\u00e7\u00e3o cansado. Al\u00e9m disso, meditar nas promessas da Escritura traz esperan\u00e7a e clareza. A Palavra \u00e9 luz para o caminho e \u00e2ncora para a alma.\nTamb\u00e9m \u00e9 importante caminhar em comunh\u00e3o. Deus nos criou para vivermos conectados, apoiando-nos uns aos outros. Uma palavra de encorajamento, um abra\u00e7o, uma ora\u00e7\u00e3o compartilhada podem reacender a f\u00e9 abatida.\nAs tribula\u00e7\u00f5es n\u00e3o t\u00eam poder de nos destruir quando estamos firmados em Cristo. Ele venceu o mundo, e n\u2019Ele tamb\u00e9m somos mais que vencedores. Confie, permane\u00e7a, adore e ver\u00e1 que, mesmo na tribula\u00e7\u00e3o, Deus faz nascer um novo amanhecer.\nMantendo-se firme!\n\nA f\u00e9 fortalece o cora\u00e7\u00e3o ao lembr\u00e1-lo das promessas de Deus, permitindo enfrentar desafios com confian\u00e7a, esperan\u00e7a renovada e certeza do constante cuidado de Deus.\nA ora\u00e7\u00e3o aproxima nossa alma do Senhor, trazendo paz profunda, dire\u00e7\u00e3o clara e for\u00e7a espiritual, mantendo-nos firmes diante das circunst\u00e2ncias adversas.\nA comunh\u00e3o fortalece nossa caminhada, oferecendo apoio m\u00fatuo, encorajamento e renova\u00e7\u00e3o, ajudando-nos a perseverar mesmo quando enfrentamos tribula\u00e7\u00f5es dif\u00edceis e desafios profundos.\n\nPara orar:\n\nSenhor, fortalece minha f\u00e9 em meio \u00e0s tribula\u00e7\u00f5es. Guarda meu cora\u00e7\u00e3o da ansiedade e renova minha esperan\u00e7a. Sustenta-me com Tua paz, guia meus passos e faz tua luz brilhar sobre mim. Am\u00e9m.\n\nVeja tamb\u00e9m: 7 raz\u00f5es para confiar em Deus em meio \u00e0s lutas.",
        "Link": "https://www.bibliaon.com/razoes_para_confiar_em_deus/"
    },
    {
        "Title": "O amor supera tudo",
        "ID": "a6e2da42d41e403fe55a3f6ffcfad512",
        "Description": "O amor \u00e9 paciente, o amor \u00e9 bondoso. N\u00e3o inveja, n\u00e3o se vangloria, n\u00e3o se orgulha.\n- 1 Cor\u00edntios 13:4\n\nTodo crist\u00e3o reconhece que o maior exemplo de amor n\u00e3o veio de palavras humanas, mas do sacrif\u00edcio perfeito de Cristo na cruz. O amor de Deus n\u00e3o depende do humor do dia, das dificuldades que enfrentamos ou das imperfei\u00e7\u00f5es que carregamos. \u00c9 um amor constante, firme e restaurador.\nQuando olhamos para Jesus, vemos um amor que abra\u00e7a o pecador, que acolhe o quebrantado e que transforma aquilo que parecia perdido. Ele nos ensina que o amor n\u00e3o \u00e9 apenas um sentimento, mas uma escolha di\u00e1ria. Escolher amar \u00e9 decidir agir com miseric\u00f3rdia quando a ofensa grita, com paci\u00eancia quando a ansiedade aperta, e com f\u00e9 quando tudo ao redor parece desmoronar.\nO amor que supera tudo \u00e9 aquele que sustenta o lar nas tempestades, que reconcilia amizades feridas e que cura feridas profundas do cora\u00e7\u00e3o. \u00c9 o amor que nos ensina a perdoar, n\u00e3o porque o outro merece, mas porque n\u00f3s tamb\u00e9m fomos perdoados pelo Pai. Deus nos chama a sermos instrumentos desse amor no mundo, um amor que ilumina, aquece e renova.\nEm cada desafio, o crist\u00e3o encontra no amor uma for\u00e7a que n\u00e3o se esgota. O amor de Deus nos levanta quando falhamos, nos guia quando estamos perdidos e nos fortalece quando somos fracos. Quando permitimos que esse amor molde nosso car\u00e1ter, passamos a enxergar as pessoas e as situa\u00e7\u00f5es pela perspectiva de Cristo.\nQue possamos viver diariamente essa verdade: o amor supera tudo, porque vem Daquele que venceu o mundo, curou nossas dores e nos chamou para amar como Ele amou. Que nossas vidas sejam reflexo desse amor que transforma e eterniza.\nVivendo um amor que supera tudo\n\nPratique gestos de amor que expressem paci\u00eancia, bondade e humildade, refletindo o car\u00e1ter de Cristo em todas as situa\u00e7\u00f5es e fortalecendo relacionamentos.\nPerdoe com sinceridade, reconhecendo que voc\u00ea tamb\u00e9m recebeu gra\u00e7a divina, permitindo que o amor de Deus restaure seu cora\u00e7\u00e3o e promova reconcilia\u00e7\u00e3o verdadeira.\nCultive comunh\u00e3o com Deus por meio da ora\u00e7\u00e3o e da Palavra, fortalecendo sua f\u00e9 e aprendendo a amar como Cristo em cada circunst\u00e2ncia.\n\nPara orar:\n\nSenhor amado, derrama teu amor sobre meu cora\u00e7\u00e3o e guia meus passos em tua paz. Fortalece minha f\u00e9, cura minhas feridas e renova minha esperan\u00e7a. Que eu viva segundo tua vontade, amando como Cristo amou, perdoando com gra\u00e7a e caminhando com confian\u00e7a. Conduz minha vida para tua gl\u00f3ria. Am\u00e9m.\n\nVeja tamb\u00e9m: As 5 caracter\u00edsticas do amor segundo a B\u00edblia.",
        "Link": "https://www.bibliaon.com/caracteristicas_do_amor/"
    }
]