[
    {
        "Title": "Palavra de Hoje (23/04/2026) - Significado completo de lixeira:",
        "ID": "7b10fd547a557039e1d6a44cbc0b0a22",
        "Description": "substantivo feminino Local onde se coloca o lixo; lixo.Lugar repugnante, asqueroso.[Figurado] Conduto vertical, que abrange a altura de um edif\u00edcio, e no qual se lan\u00e7a o lixo dom\u00e9stico de cada andar.Etimologia (origem da palavra lixeira). A palavra lixeira com sentido de lixo, tem sua origem pela jun\u00e7\u00e3o de lixo, e do sufixo -eira.substantivo feminino [Regionalismo: Mato Grosso e Mato Grosso do Sul] Nome comum dado ao cajueiro-bravo; cajupeba, cambarba, craibeira, penteeira, pentieira, samba\u00edba.Etimologia (origem da palavra lixeira). A palavra lixeira com sentido de cajueiro tem sua origem pela jun\u00e7\u00e3o de lixa, e do sufixo -eira.\n \nSin\u00f4nimos:\n\nesterqueira, alfurja, monturo, alfuja, busilh\u00e3o, cadoz, chafurda \n",
        "Link": "https://www.dicio.com.br/lixeira/"
    },
    {
        "Title": "Palavra de Ontem (22/04/2026) - Significado completo de alameda:",
        "ID": "e8adee62c747b8bb4d0971176c27069a",
        "Description": "Sin\u00f4nimos:\n\nesterqueira, alfurja, monturo, alfuja, busilh\u00e3o, cadoz, chafurda\n Classe gramatical:substantivo feminino",
        "Link": "https://www.dicio.com.br/alameda/"
    },
    {
        "Title": "Palavra de Anteontem (21/04/2026) - Significado completo de coelho:",
        "ID": "6eada5e980321f22728a92b87aa792b5",
        "Description": "Classe gramatical:substantivo feminino\n S\u00edlabas:li-xei-ra",
        "Link": "https://www.dicio.com.br/coelho/"
    }
]