[
    {
        "Title": "Palavra de Hoje (20/01/2026) - Significado completo de inf\u00e2ncia:",
        "ID": "10eb1862b8a3881d5f5d97eb31fdf21c",
        "Description": "substantivo feminino Per\u00edodo inicial da vida humana que vai do nascimento at\u00e9 ao in\u00edcio da adolesc\u00eancia, geralmente a partir dos 12 anos.As crian\u00e7as; o n\u00famero total de crian\u00e7as em: a inf\u00e2ncia mineira.[Figurado] Come\u00e7o de alguma coisa; origem: a inf\u00e2ncia do mundo.Etimologia (origem da palavra inf\u00e2ncia). A palavra inf\u00e2ncia deriva do latim \u201cinfantia,ae\u201d, com o mesmo sentido.\n \nSin\u00f4nimos:\n\npuer\u00edcia, meninice, meninada, garotice \n",
        "Link": "https://www.dicio.com.br/infancia/"
    },
    {
        "Title": "Palavra de Ontem (19/01/2026) - Significado completo de proselitismo:",
        "ID": "3b725a267ee4905e4c56568682766197",
        "Description": "Sin\u00f4nimos:\n\npuer\u00edcia, meninice, meninada, garotice\n \nAnt\u00f4nimos:\n\nvelhice \n",
        "Link": "https://www.dicio.com.br/proselitismo/"
    },
    {
        "Title": "Palavra de Anteontem (18/01/2026) - Significado completo de aspecto:",
        "ID": "c3098f63432bf0567b0a6dec52cced54",
        "Description": "Ant\u00f4nimos:\n\nvelhice\n Classe gramatical:substantivo feminino",
        "Link": "https://www.dicio.com.br/aspecto/"
    }
]