[
    {
        "Title": "Palavra de Hoje (13/12/2025) - Significado completo de hidr\u00f3xido:",
        "ID": "e67f0f8ef6cb226f71df5ad6a419b61a",
        "Description": "substantivo masculino [Qu\u00edmica] Designa\u00e7\u00e3o comum dos compostos, especialmente bases, que possuem hidroxila ou oxidrila (OH-).express\u00e3o Hidr\u00f3xido de am\u00f4nia. Subst\u00e2ncia obtida a partir da dilui\u00e7\u00e3o do amon\u00edaco em \u00e1gua (NH4 OH).Hidr\u00f3xido de pot\u00e1ssio. Reagente usado na fabrica\u00e7\u00e3o de sab\u00e3o; potassa.Hidr\u00f3xido de s\u00f3dio. Designa\u00e7\u00e3o de soda c\u00e1ustica (NaOH), usada com os mais variados prop\u00f3sitos.Etimologia (origem da palavra hidr\u00f3xido). Hidro- + \u00f3xido.\n Classe gramatical:substantivo masculino",
        "Link": "https://www.dicio.com.br/hidroxido/"
    },
    {
        "Title": "Palavra de Ontem (12/12/2025) - Significado completo de indedut\u00edvel:",
        "ID": "390a52c29c501880f0467e1f279a0fb8",
        "Description": "Classe gramatical:substantivo masculino\n S\u00edlabas:hi-dr\u00f3-xi-do",
        "Link": "https://www.dicio.com.br/indedutivel/"
    },
    {
        "Title": "Palavra de Anteontem (11/12/2025) - Significado completo de arlequim:",
        "ID": "bc38a1aa72aae5558197392f2084e7e4",
        "Description": "S\u00edlabas:hi-dr\u00f3-xi-do\n \nAnt\u00f4nimos:\n\ndedut\u00edvel \n",
        "Link": "https://www.dicio.com.br/arlequim/"
    }
]